LICENSE
nonebot_plugin_autohelp/__init__.py
nonebot_plugin_autohelp/fetch_plugin_info.py
nonebot_plugin_autohelp/nonebot_plugin_autohelp.py
nonebot_plugin_autohelp/nonebot_plugin_autohelp.py-
nonebot_plugin_autohelp/parse_cmd.py
nonebot_plugin_autohelp-0.1.6.dist-info/LICENSE
nonebot_plugin_autohelp-0.1.6.dist-info/WHEEL
nonebot_plugin_autohelp-0.1.6.dist-info/METADATA
nonebot_plugin_autohelp-0.1.6.dist-info/RECORD
