Metadata-Version: 2.1
Name: nonebot-plugin-autohelp
Version: 0.1.6
Summary: nonebot2 plugin 自动生成载入插件的帮助信息，响应 /help !help help 菜单 caidan /i
Home-page: https://github.com/ffreemt/nonebot-plugin-autohelp
License: MIT
Author: ffreemt
Requires-Python: >=3.7.3,<4.0.0
Classifier: License :: OSI Approved :: MIT License
Classifier: Programming Language :: Python :: 3
Classifier: Programming Language :: Python :: 3.10
Classifier: Programming Language :: Python :: 3.8
Classifier: Programming Language :: Python :: 3.9
Requires-Dist: logzero (>=1.7.0,<2.0.0)
Requires-Dist: nonebot-adapter-onebot (>=2.0.0-beta.1,<3.0.0)
Requires-Dist: nonebot2 (>=2.0.0-alpha.16,<3.0.0)
Project-URL: Repository, https://github.com/ffreemt/nonebot-plugin-autohelp
